vlab4micjupyter/__init__.py
vlab4micjupyter/_experiment_parameters.py
vlab4micjupyter/_experiment_visualisation.py
vlab4micjupyter/_widget_generator.py
vlab4micjupyter/experiment_widgets.py
vlab4micjupyter/matplotlib_plots.py
vlab4micjupyter/sweep_parameters_widgets.py
vlab4micjupyter-0.0.6.dist-info/licenses/LICENSE.txt
vlab4micjupyter-0.0.6.dist-info/METADATA
vlab4micjupyter-0.0.6.dist-info/WHEEL
vlab4micjupyter-0.0.6.dist-info/top_level.txt
vlab4micjupyter-0.0.6.dist-info/RECORD
